yapyang/__init__.py
yapyang/constants.py
yapyang/nodes.py
yapyang/utils.py
yapyang/version.py
yapyang-0.2.0.dist-info/LICENSE
yapyang-0.2.0.dist-info/METADATA
yapyang-0.2.0.dist-info/WHEEL
yapyang-0.2.0.dist-info/RECORD
