Metadata-Version: 2.3
Name: yapyang
Version: 0.2.0
Summary: An open source Python package that helps developers to translate YANG (RFC6020/RFC7950) data models to Python.
License: Apache-2.0
Author: a.faria
Author-email: antonio.faria@nomios.co.uk
Requires-Python: >=3.9,<4.0
Classifier: License :: OSI Approved :: Apache Software License
Classifier: Programming Language :: Python :: 3
Classifier: Programming Language :: Python :: 3.9
Classifier: Programming Language :: Python :: 3.10
Classifier: Programming Language :: Python :: 3.11
Classifier: Programming Language :: Python :: 3.12
Classifier: Programming Language :: Python :: 3.13
Requires-Dist: ordered-set (>=4.1.0,<5.0.0)
Project-URL: Documentation, https://nomios-opensource.github.io/yapyang
Project-URL: Repository, https://github.com/nomios-opensource/yapyang
